{"F": [[["me", "good morning"], ["her", "good morninggg :)"], ["her", "i had a dream about you lol"], ["me", "oh yeah? what happened"], ["her", "wouldnt you like to know ;)"], ["me", "you cant just say that and not tell me"], ["her", "maybe ill tell you in person"], ["me", "is that an invitation"], ["her", "maybe it is"], ["her", "what are you doing this weekend btw"]], [["her", "hiii"], ["her", "hello??"], ["me", "hey sorry was in class"], ["her", "i forgive you this time"], ["me", "so generous"], ["her", "i know right"], ["her", "anyway look at this"], ["her", "sent a photo"], ["me", "wait you look so good"], ["her", "stop ittt"], ["her", "ok dont stop"], ["me", "lmaooo"], ["her", "youre cute"]], [["me", "that meme you sent me earlier had me dying"], ["her", "i literally saw it and thought of you immediately"], ["me", "you think of me?"], ["her", "shut up"], ["her", "yes obviously"], ["me", "good because same"], ["her", "omg stoppp"], ["her", "jk dont stop"], ["me", "youre sending mixed signals rn"], ["her", "thats my specialty <3"]], [["her", "quick question"], ["me", "shoot"], ["her", "are you free tomorrow night"], ["me", "for you? always"], ["her", "smooth"], ["her", "ok so theres this new ramen place"], ["me", "say less im there"], ["her", "yayy its a date then"], ["me", "a date huh"], ["her", "i mean"], ["her", "yeah a date"], ["her", "is that ok"], ["me", "more than ok"], ["her", "ok good :)))"]], [["me", "hey how was your day"], ["her", "so much better now that you texted me"], ["me", "that was smooth"], ["her", "learned from the best"], ["me", "who taught you"], ["her", "you dummy"], ["me", "oh"], ["me", "OH"], ["her", "lmaoooo your reaction"], ["her", "adorable"]], [["her", "i cant sleep"], ["me", "same tbh"], ["her", "what are you thinking about"], ["me", "honestly?"], ["her", "honestly"], ["me", "you"], ["her", "..."], ["her", "thats the cutest thing anyones ever said to me"], ["me", "i try"], ["her", "you dont even have to try"], ["her", "it just comes naturally with you"]]], "D": [[["me", "hey hows it going"], ["her", "good"], ["me", "do anything fun today?"], ["her", "not really"], ["me", "want to do something later?"], ["her", "maybe"], ["me", "just let me know!"], ["her", "k"]], [["me", "good morning! hope you have an amazing day"], ["her", "thanks"], ["me", "any plans for today?"], ["her", "busy"], ["me", "ah gotcha no worries"]], [["me", "hey did you see that show I recommended?"], ["her", "no"], ["me", "you should check it out its really good"], ["her", "ok"], ["me", "the third episode is insane"], ["her", "cool"]], [["me", "heyy"], ["her", "hi"], ["me", "what are you up to"], ["her", "stuff"], ["me", "lol very descriptive"], ["her", "lol"]], [["me", "that concert next week looks so good we should go"], ["her", "idk"], ["me", "come on itll be fun"], ["her", "ill think about it"], ["me", "ok just lmk"]], [["her", "hey"], ["me", "heyyy whats up!!"], ["her", "nm"], ["me", "wanna hang out this weekend?"], ["her", "well see"], ["me", "ok sounds good!"]], [["me", "how was your exam"], ["her", "fine"], ["me", "did you feel good about it?"], ["her", "i guess"], ["me", "im sure you killed it"], ["her", "thanks"]]], "L": [[["me", "hey!"], ["me", "hope your day is going well"]], [["me", "yo did you get my last message"], ["me", "no worries if youre busy"]], [["me", "good morning!"], ["me", "found this place that has the best coffee youd love it"], ["me", "anyway hope you have a good day"]], [["me", "hey so about this weekend"], ["me", "were you still thinking about going?"], ["me", "all good either way just lmk"]], [["me", "that song you showed me has been stuck in my head all day"]], [["me", "heyy havent heard from you in a bit"], ["me", "hope everythings ok"]], [["me", "just saw something that reminded me of you lol"], ["me", "sent a photo"]]], "S": [[["her", "https://open.spotify.com/track/3ee8Jmje8o58CHK66QFRcY"]], [["her", "https://open.spotify.com/track/7qiZfU4dY1lWllzX7mPBI3"]], [["her", "listen to this rn"], ["her", "https://open.spotify.com/track/0VjIjW4GlUZAMYd2vXMi3b"]], [["her", "this song is you"], ["her", "https://open.spotify.com/track/2TpxZ7JUBn3uw46aR7qd6V"]], [["her", "https://open.spotify.com/track/4uLU6hMCjMI75M1A2tKUQC"], ["her", "idk why i thought of you"]], [["her", "https://open.spotify.com/track/6UelLqGlWMcVH1E5c4H7lY"], ["her", "..."]]], "N": [[["me", "hey did you eat yet"], ["her", "yeah just had chipotle"], ["me", "nice what did you get"], ["her", "bowl with extra guac obviously"], ["me", "obviously"], ["her", "wbu"], ["me", "havent eaten yet might just make ramen"], ["her", "living your best life"]], [["her", "can you help me with something"], ["me", "of course whats up"], ["her", "how do you convert a pdf to word"], ["me", "just use google docs open the pdf and download as docx"], ["her", "omg thank you youre a lifesaver"], ["me", "anytime"]], [["me", "class was so boring today"], ["her", "which one"], ["me", "econ"], ["her", "ugh i feel that"], ["me", "prof literally read off the slides for an hour"], ["her", "why do they even make slides then"], ["me", "right??"], ["her", "at least its over now"]], [["her", "did you watch the game last night"], ["me", "yes bro that ending was insane"], ["her", "dont bro me lol"], ["me", "my bad"], ["her", "lol youre good"], ["me", "that buzzer beater though"], ["her", "literally screamed"]], [["me", "what time is the study group tomorrow"], ["her", "i think 3pm at the library"], ["me", "cool ill be there"], ["her", "bring snacks"], ["me", "say less"], ["her", "youre the best"]], [["her", "ugh today was so long"], ["me", "what happened"], ["her", "just everything piling up you know"], ["me", "yeah i get that. want to talk about it?"], ["her", "nah ill be fine thanks though"], ["me", "ok well im here if you need anything"], ["her", "i know. thanks"]], [["me", "the weather is insane rn"], ["her", "i know i almost got blown away walking to class"], ["me", "lmaooo"], ["her", "its not funny i was literally holding onto a pole"], ["me", "im sorry but that mental image is hilarious"], ["her", "youre the worst"], ["me", "you love it"], ["her", "debatable"]]], "H": [[["her", "hey i missed you today"], ["me", "aww i missed you too"], ["her", "we should hang out soon"], ["me", "yes!! when are you free"], ["her", "ill check my schedule"], ["me", "ok sounds good!"], ["me", "did you check your schedule?"], ["her", "oh yeah idk i might be busy"], ["me", "oh ok no worries"], ["her", "yeah sorry"]], [["her", "you looked really good today btw"], ["me", "wait really? thanks"], ["her", "yeah that jacket is nice"], ["me", "you should see the rest of my wardrobe then"], ["her", "lol ok"], ["me", "was that a compliment or were you just being nice"], ["her", "idk"], ["me", "helpful"], ["her", "lol"]], [["me", "hey we should get dinner this week"], ["her", "omg yes id love that"], ["her", "theres this new thai place"], ["me", "perfect lets do thursday"], ["her", "wait actually i forgot i have a thing thursday"], ["me", "friday?"], ["her", "ill let you know"], ["me", "ok!"], ["me", "hey did you figure out friday?"], ["her", "sorry been super busy. maybe next week?"]], [["her", "i told my friends about you"], ["me", "oh really? what did you say"], ["her", "just that youre cool"], ["me", "just cool?"], ["her", "what do you want me to say lol"], ["me", "idk something nicer than cool"], ["her", "youre fine"], ["me", "fine as in good looking or fine as in just ok"], ["her", "lol goodnight"]], [["her", "sent a photo"], ["her", "do i look ok for tonight"], ["me", "you look amazing where are you going"], ["her", "just out with friends"], ["me", "have fun!"], ["her", "thanks!"], ["me", "text me when you get home safe?"], ["her", "well see lol"]]], "G": [[["her", "hey were all going to karaoke friday you should come"], ["me", "wait that sounds so fun im in"], ["her", "nice! its gonna be me sarah jake and a few others"], ["me", "perfect"], ["her", "do you know any good songs"], ["me", "i have a few in mind"], ["her", "you better not embarrass me"], ["me", "no promises"], ["her", "lmaooo"]], [["me", "hey a bunch of us are going bowling saturday"], ["her", "whos going"], ["me", "mike, sarah, alex, maybe a few more"], ["her", "hmm maybe"], ["me", "come on itll be fun"], ["her", "fine but only if theres food"], ["me", "obviously theres food"], ["her", "ok then im in"]]]}